odoo10_addon_account_balance_reporting-10.0.1.4.0-py2.7-nspkg.pth
odoo/addons/account_balance_reporting/README.rst
odoo/addons/account_balance_reporting/__init__.py
odoo/addons/account_balance_reporting/__manifest__.py
odoo/addons/account_balance_reporting/i18n/bg.po
odoo/addons/account_balance_reporting/i18n/ca.po
odoo/addons/account_balance_reporting/i18n/ca_ES.po
odoo/addons/account_balance_reporting/i18n/cs.po
odoo/addons/account_balance_reporting/i18n/de.po
odoo/addons/account_balance_reporting/i18n/es.po
odoo/addons/account_balance_reporting/i18n/es_CO.po
odoo/addons/account_balance_reporting/i18n/es_CR.po
odoo/addons/account_balance_reporting/i18n/es_ES.po
odoo/addons/account_balance_reporting/i18n/eu.po
odoo/addons/account_balance_reporting/i18n/fr.po
odoo/addons/account_balance_reporting/i18n/gl.po
odoo/addons/account_balance_reporting/i18n/hr.po
odoo/addons/account_balance_reporting/i18n/nl.po
odoo/addons/account_balance_reporting/i18n/pl.po
odoo/addons/account_balance_reporting/i18n/pt.po
odoo/addons/account_balance_reporting/i18n/pt_BR.po
odoo/addons/account_balance_reporting/i18n/ru.po
odoo/addons/account_balance_reporting/i18n/sl.po
odoo/addons/account_balance_reporting/i18n/sv.po
odoo/addons/account_balance_reporting/i18n/tr.po
odoo/addons/account_balance_reporting/i18n/vi.po
odoo/addons/account_balance_reporting/models/__init__.py
odoo/addons/account_balance_reporting/models/account_balance_reporting_report.py
odoo/addons/account_balance_reporting/models/account_balance_reporting_template.py
odoo/addons/account_balance_reporting/report/account_balance_reporting_reports.xml
odoo/addons/account_balance_reporting/report/report_generic.xml
odoo/addons/account_balance_reporting/security/ir.model.access.csv
odoo/addons/account_balance_reporting/static/description/icon.png
odoo/addons/account_balance_reporting/static/description/icon.svg
odoo/addons/account_balance_reporting/tests/__init__.py
odoo10_addon_account_balance_reporting-10.0.1.4.0.dist-info/DESCRIPTION.rst
odoo10_addon_account_balance_reporting-10.0.1.4.0.dist-info/METADATA
odoo10_addon_account_balance_reporting-10.0.1.4.0.dist-info/RECORD
odoo10_addon_account_balance_reporting-10.0.1.4.0.dist-info/WHEEL
odoo10_addon_account_balance_reporting-10.0.1.4.0.dist-info/metadata.json
odoo10_addon_account_balance_reporting-10.0.1.4.0.dist-info/namespace_packages.txt
odoo10_addon_account_balance_reporting-10.0.1.4.0.dist-info/top_level.txt
