Metadata-Version: 2.0
Name: odoo10-addon-account-balance-reporting
Version: 10.0.1.4.0
Summary: Account balance reporting engine
Home-page: http://www.pexego.es
Author: Pexego, AvanzOSC, Tecnativa, Odoo Community Association (OCA)
Author-email: support@odoo-community.org
License: AGPL-3
Platform: UNKNOWN
Classifier: Programming Language :: Python
Classifier: Framework :: Odoo
Classifier: License :: OSI Approved :: GNU Affero General Public License v3
Requires-Python: ~=2.7
Requires-Dist: odoo (<10.1dev,>=10.0)
Requires-Dist: odoo10-addon-date-range
